example_pkg/001---test.py
example_pkg/__init__.py
tay_test-0.0.3.dist-info/LICENSE
tay_test-0.0.3.dist-info/METADATA
tay_test-0.0.3.dist-info/WHEEL
tay_test-0.0.3.dist-info/top_level.txt
tay_test-0.0.3.dist-info/RECORD
