Metadata-Version: 2.1
Name: tay-test
Version: 0.0.3
Summary: Tay的一个简单测试
Home-page: https://gitee.com/tay3223/tmp.git
Author: 古寒飞
Author-email: tay3223@qq.com
License: UNKNOWN
Platform: UNKNOWN
Classifier: Programming Language :: Python :: 3
Classifier: License :: OSI Approved :: MIT License
Classifier: Operating System :: OS Independent
Requires-Python: >=3.6
